dybuf/__init__.py
dybuf/_core.c
dybuf/_core.cp311-win_amd64.pyd
dybuf/_core.pxd
dybuf/_core.pyx
dybuf/tests/__init__.py
dybuf/tests/test_roundtrip.py
dybuf-0.3.0.dist-info/licenses/LICENSE
dybuf-0.3.0.dist-info/METADATA
dybuf-0.3.0.dist-info/WHEEL
dybuf-0.3.0.dist-info/top_level.txt
dybuf-0.3.0.dist-info/RECORD
