Metadata-Version: 2.1
Name: dybuf
Version: 0.3.0
Summary: Python bindings for the dybuf dynamic buffer library.
Author-email: Yuchi <yuchi518@gmail.com>
Maintainer-email: Yuchi <yuchi518@gmail.com>
License: dybuf, dynamic buffer library
Project-URL: Homepage, https://github.com/yuchi518/dybuf
Project-URL: Issues, https://github.com/yuchi518/dybuf/issues
Keywords: buffer,binary,cython
Classifier: Development Status :: 3 - Alpha
Classifier: Intended Audience :: Developers
Classifier: License :: OSI Approved :: GNU General Public License v2 (GPLv2)
Classifier: Operating System :: OS Independent
Classifier: Programming Language :: Python :: 3
Classifier: Programming Language :: Python :: 3 :: Only
Classifier: Programming Language :: C
Classifier: Programming Language :: Cython
Classifier: Topic :: Software Development :: Libraries :: Python Modules
Requires-Python: >=3.8
License-File: LICENSE
